Metadata-Version: 2.1
Name: cmd.pypi
Version: 0.1
Summary: My CMD 模組
Home-page: https://gitlab.com/moon-start/cmd.py
Author: moon-start
Author-email: login0516mp4@gmail.com
License: LGPL
Platform: UNKNOWN
